prideflags/__init__.py
prideflags/flags.py
prideflags/utils.py
prideflags-0.1.0.dist-info/LICENSE
prideflags-0.1.0.dist-info/METADATA
prideflags-0.1.0.dist-info/WHEEL
prideflags-0.1.0.dist-info/top_level.txt
prideflags-0.1.0.dist-info/RECORD
