Metadata-Version: 2.1
Name: prideflags
Version: 0.1.0
Summary: prideflags library for python 3.9+
Author-email: sctech <gamerselimiko@gmail.com>
Project-URL: source, https://git.gay/sctech/prideflags
Classifier: Programming Language :: Python :: 3
Classifier: Programming Language :: Python :: 3.12
Classifier: Programming Language :: Python :: 3.13
Classifier: Programming Language :: Python :: 3.9
Classifier: License :: OSI Approved :: GNU Affero General Public License v3 or later (AGPLv3+)
Classifier: Operating System :: OS Independent
Requires-Python: >=3.9
License-File: LICENSE
